MANIFEST.in
README
setup.py
bin/jsonschema_generator.py
json_schema_generator/__init__.py
json_schema_generator/generator.py
json_schema_generator/recorder.py
json_schema_generator/schema_types.py
json_schema_generator/test_template.py.tmpl
json_schema_generator/validator.py
json_schema_generator.egg-info/PKG-INFO
json_schema_generator.egg-info/SOURCES.txt
json_schema_generator.egg-info/dependency_links.txt
json_schema_generator.egg-info/not-zip-safe
json_schema_generator.egg-info/requires.txt
json_schema_generator.egg-info/top_level.txt