Metadata-Version: 1.0
Name: json-schema-generator
Version: 0.3
Summary: A simple json schema generator based on json resource with auto validation tools
Home-page: https://pypi.python.org/pypi/json_schema_generator/
Author: Felipe Ramos Ferreira
Author-email: perenecabuto@gmail.com
License: UNKNOWN
Keywords: json_schema,jsonschema,json,generator,api,validator
Platform: UNKNOWN
Classifier: Development Status :: 4 - Beta
Classifier: Environment :: Console
Classifier: Intended Audience :: Developers
Classifier: Intended Audience :: Information Technology
Classifier: Intended Audience :: System Administrators
Classifier: License :: OSI Approved :: GNU General Public License v3 (GPLv3)
Classifier: Natural Language :: English
Classifier: Operating System :: OS Independent
Classifier: Programming Language :: Python
Classifier: Programming Language :: Python :: 2.7
Classifier: Topic :: Software Development :: Code Generators
Classifier: Topic :: Software Development :: Quality Assurance
Classifier: Topic :: Software Development :: Testing
